awca/__init__.py
awca/ocr.py
awca/paraphrasing.py
awca/summarization.py
awca-0.0.3.2.dist-info/LICENSE
awca-0.0.3.2.dist-info/METADATA
awca-0.0.3.2.dist-info/WHEEL
awca-0.0.3.2.dist-info/top_level.txt
awca-0.0.3.2.dist-info/RECORD
