Metadata-Version: 2.1
Name: awca
Version: 0.0.3.2
Summary: A toolkit for making ancient world citation analysis, text summarization, paraphrasing and OCR for PDF to CSV
Home-page: https://github.com/UmbraVenus/awca-tools
Author: Sage Ren (Umbra Venus)
Author-email: sage.shijie.ren@gmail.com
License: MIT
Platform: UNKNOWN
Requires-Python: >=3.6
License-File: LICENSE
Requires-Dist: poppler-utils
Requires-Dist: pdf2image
Requires-Dist: pytesseract
Requires-Dist: pillow
Requires-Dist: PyPDF3
Requires-Dist: torch
Requires-Dist: transformers (==3.1.0)
